README.md
setup.py
planfix_py/__init__.py
planfix_py/api.py
planfix_py.egg-info/PKG-INFO
planfix_py.egg-info/SOURCES.txt
planfix_py.egg-info/dependency_links.txt
planfix_py.egg-info/not-zip-safe
planfix_py.egg-info/requires.txt
planfix_py.egg-info/top_level.txt