Metadata-Version: 2.1
Name: planfix-py
Version: 0.2.2
Summary: Python package for working with Planfix API
Home-page: https://github.com/LD31D/planfix_py
Author: LD31D
Author-email: artem.12m21@gmail.com
License: MIT
Platform: UNKNOWN
